selfreplicator/__init__.py
selfreplicator/__main__.py
selfreplicator/analyze.py
selfreplicator/cli.py
selfreplicator/models.py
selfreplicator/shapes.py
selfreplicator/tests.py
selfreplicator/training.py
selfreplicator-0.1.0.dist-info/entry_points.txt
selfreplicator-0.1.0.dist-info/WHEEL
selfreplicator-0.1.0.dist-info/METADATA
selfreplicator-0.1.0.dist-info/RECORD
