Metadata-Version: 2.1
Name: selfreplicator
Version: 0.1.0
Summary: 
Author: ParsaGhadermazi
Author-email: 54489047+ParsaGhadermazi@users.noreply.github.com
Requires-Python: >=3.10,<4.0
Classifier: Programming Language :: Python :: 3
Classifier: Programming Language :: Python :: 3.10
Requires-Dist: numpy (>=2.1.3,<3.0.0)
Requires-Dist: pandas (>=2.2.3,<3.0.0)
Requires-Dist: plotly (>=5.24.1,<6.0.0)
Requires-Dist: ray (>=2.39.0,<3.0.0)
Requires-Dist: torch (>=2.5.1,<3.0.0)
